djangocms_conditional/__init__.py
djangocms_conditional/cms_plugins.py
djangocms_conditional/models.py
djangocms_conditional/migrations/0001_initial.py
djangocms_conditional/migrations/0002_conditionalpluginmodel_mode.py
djangocms_conditional/migrations/__init__.py
djangocms_conditional/templates/djangocms_conditional/conditional.html
djangocms_conditional-0.2.1.dist-info/DESCRIPTION.rst
djangocms_conditional-0.2.1.dist-info/METADATA
djangocms_conditional-0.2.1.dist-info/RECORD
djangocms_conditional-0.2.1.dist-info/WHEEL
djangocms_conditional-0.2.1.dist-info/metadata.json
djangocms_conditional-0.2.1.dist-info/top_level.txt
