Metadata-Version: 2.0
Name: djangocms-conditional
Version: 0.2.1
Summary: django CMS plugin that shows content based on user group membership.
Home-page: https://github.com/rhooper/djangocms-conditional
Author: Roy Hooper
Author-email: rhooper@toybox.ca
License: GPLv2+
Keywords: djangocms-conditional
Platform: UNKNOWN
Classifier: Development Status :: 2 - Pre-Alpha
Classifier: Framework :: Django
Classifier: Intended Audience :: Developers
Classifier: License :: OSI Approved :: BSD License
Classifier: Natural Language :: English
Classifier: Programming Language :: Python :: 3
Classifier: Programming Language :: Python :: 3.6
Requires-Dist: django-cms (>=3.4)
